j_kuant/__init__.py
j_kuant/core.py
j_kuant/utils.py
j_kuant-0.1.13.dist-info/licenses/LICENSE
tests/test_core.py
j_kuant-0.1.13.dist-info/METADATA
j_kuant-0.1.13.dist-info/WHEEL
j_kuant-0.1.13.dist-info/top_level.txt
j_kuant-0.1.13.dist-info/RECORD
