Metadata-Version: 2.4
Name: j_kuant
Version: 0.1.13
Summary: A test package for Jupyter-based quantum work
Author-email: Jeremy <jeremy@vconn.org>
License-Expression: MIT
Requires-Python: >=3.7
License-File: LICENSE
Dynamic: license-file
